{"Entities": [{"Id": 1, "BeginOffset": 95, "EndOffset": 108, "Score": 0.45078256726264954, "Text": "United States", "Category": "PROTECTED_HEALTH_INFORMATION", "Type": "ADDRESS", "Traits": []}, {"Id": 2, "BeginOffset": 110, "EndOffset": 114, "Score": 0.8003188967704773, "Text": "2021", "Category": "PROTECTED_HEALTH_INFORMATION", "Type": "DATE", "Traits": []}, {"Id": 3, "BeginOffset": 124, "EndOffset": 141, "Score": 0.997405469417572, "Text": "February 10, 2023", "Category": "PROTECTED_HEALTH_INFORMATION", "Type": "DATE", "Traits": []}, {"Id": 4, "BeginOffset": 161, "EndOffset": 177, "Score": 0.9998175501823425, "Text": "Deborah M. Stone", "Category": "PROTECTED_HEALTH_INFORMATION", "Type": "NAME", "Traits": []}, {"Id": 5, "BeginOffset": 185, "EndOffset": 198, "Score": 0.9965851306915283, "Text": "Karin A. Mack", "Category": "PROTECTED_HEALTH_INFORMATION", "Type": "NAME", "Traits": []}, {"Id": 6, "BeginOffset": 206, "EndOffset": 221, "Score": 0.9977756142616272, "Text": "Judith Qualters", "Category": "PROTECTED_HEALTH_INFORMATION", "Type": "NAME", "Traits": []}, {"Id": 52, "BeginOffset": 373, "EndOffset": 380, "Score": 0.7269155979156494, "Text": "Suicide", "Category": "MEDICAL_CONDITION", "Type": "DX_NAME", "Traits": [{"Name": "SYMPTOM", "Score": 0.5035590529441833}]}, {"Id": 7, "BeginOffset": 423, "EndOffset": 436, "Score": 0.9567785859107971, "Text": "United States", "Category": "PROTECTED_HEALTH_INFORMATION", "Type": "ADDRESS", "Traits": []}, {"Id": 53, "BeginOffset": 479, "EndOffset": 486, "Score": 0.49105218052864075, "Text": "suicide", "Category": "MEDICAL_CONDITION", "Type": "DX_NAME", "Traits": []}, {"Id": 8, "BeginOffset": 498, "EndOffset": 502, "Score": 0.992763102054596, "Text": "2019", "Category": "PROTECTED_HEALTH_INFORMATION", "Type": "DATE", "Traits": []}, {"Id": 9, "BeginOffset": 517, "EndOffset": 521, "Score": 0.8420618176460266, "Text": "2020", "Category": "PROTECTED_HEALTH_INFORMATION", "Type": "DATE", "Traits": []}, {"Id": 10, "BeginOffset": 524, "EndOffset": 528, "Score": 0.38940441608428955, "Text": "2021", "Category": "PROTECTED_HEALTH_INFORMATION", "Type": "DATE", "Traits": []}, {"Id": 54, "BeginOffset": 558, "EndOffset": 565, "Score": 0.5756175518035889, "Text": "suicide", "Category": "MEDICAL_CONDITION", "Type": "DX_NAME", "Traits": []}, {"Id": 11, "BeginOffset": 601, "EndOffset": 605, "Score": 0.9977364540100098, "Text": "2018", "Category": "PROTECTED_HEALTH_INFORMATION", "Type": "DATE", "Traits": []}, {"Id": 68, "BeginOffset": 628, "EndOffset": 645, "Score": 0.5247095227241516, "Text": "age-adjusted rate", "Category": "TEST_TREATMENT_PROCEDURE", "Type": "TEST_NAME", "Traits": [], "Attributes": [{"Type": "TEST_VALUE", "Score": 0.5639317035675049, "RelationshipScore": 0.9998990297317505, "RelationshipType": "TEST_VALUE", "Id": 69, "BeginOffset": 649, "EndOffset": 653, "Text": "14.1", "Category": "TEST_TREATMENT_PROCEDURE", "Traits": []}]}, {"Id": 12, "BeginOffset": 702, "EndOffset": 706, "Score": 0.9998319149017334, "Text": "2018", "Category": "PROTECTED_HEALTH_INFORMATION", "Type": "DATE", "Traits": []}, {"Id": 13, "BeginOffset": 883, "EndOffset": 892, "Score": 0.986974835395813, "Text": "2018\u20132021", "Category": "PROTECTED_HEALTH_INFORMATION", "Type": "DATE", "Traits": []}, {"Id": 14, "BeginOffset": 1005, "EndOffset": 1014, "Score": 0.8834730982780457, "Text": "2018\u20132021", "Category": "PROTECTED_HEALTH_INFORMATION", "Type": "DATE", "Traits": []}, {"Id": 15, "BeginOffset": 1386, "EndOffset": 1390, "Score": 0.9105972051620483, "Text": "2018", "Category": "PROTECTED_HEALTH_INFORMATION", "Type": "DATE", "Traits": []}, {"Id": 55, "BeginOffset": 1432, "EndOffset": 1438, "Score": 0.5236773490905762, "Text": "deaths", "Category": "MEDICAL_CONDITION", "Type": "DX_NAME", "Traits": [{"Name": "HYPOTHETICAL", "Score": 0.5716336369514465}]}, {"Id": 70, "BeginOffset": 1450, "EndOffset": 1458, "Score": 0.6012560725212097, "Text": "p-values", "Category": "TEST_TREATMENT_PROCEDURE", "Type": "TEST_NAME", "Traits": [], "Attributes": [{"Type": "TEST_VALUE", "Score": 0.8135533332824707, "RelationshipScore": 0.9838320016860962, "RelationshipType": "TEST_VALUE", "Id": 71, "BeginOffset": 1459, "EndOffset": 1464, "Text": "<0.05", "Category": "TEST_TREATMENT_PROCEDURE", "Traits": []}]}, {"Id": 16, "BeginOffset": 1825, "EndOffset": 1831, "Score": 0.9320352673530579, "Text": "Alaska", "Category": "PROTECTED_HEALTH_INFORMATION", "Type": "ADDRESS", "Traits": []}, {"Id": 17, "BeginOffset": 1957, "EndOffset": 1966, "Score": 0.6299083232879639, "Text": "2018\u20132021", "Category": "PROTECTED_HEALTH_INFORMATION", "Type": "DATE", "Traits": []}, {"Id": 18, "BeginOffset": 2236, "EndOffset": 2245, "Score": 0.2126072198152542, "Text": "2018\u20132021", "Category": "PROTECTED_HEALTH_INFORMATION", "Type": "DATE", "Traits": []}, {"Id": 73, "BeginOffset": 2334, "EndOffset": 2346, "Score": 0.635490894317627, "Text": "rate decline", "Category": "TEST_TREATMENT_PROCEDURE", "Type": "TREATMENT_NAME", "Traits": []}, {"Id": 19, "BeginOffset": 2369, "EndOffset": 2373, "Score": 0.9665178060531616, "Text": "2018", "Category": "PROTECTED_HEALTH_INFORMATION", "Type": "DATE", "Traits": []}, {"Id": 20, "BeginOffset": 2487, "EndOffset": 2496, "Score": 0.8955696821212769, "Text": "2018\u20132021", "Category": "PROTECTED_HEALTH_INFORMATION", "Type": "DATE", "Traits": []}, {"Id": 56, "BeginOffset": 2933, "EndOffset": 2952, "Score": 0.3805389404296875, "Text": "significant changes", "Category": "MEDICAL_CONDITION", "Type": "DX_NAME", "Traits": [{"Name": "SIGN", "Score": 0.6076013445854187}]}, {"Id": 21, "BeginOffset": 3176, "EndOffset": 3180, "Score": 0.9912620782852173, "Text": "2018", "Category": "PROTECTED_HEALTH_INFORMATION", "Type": "DATE", "Traits": []}, {"Id": 57, "BeginOffset": 3371, "EndOffset": 3378, "Score": 0.73572838306427, "Text": "Suicide", "Category": "MEDICAL_CONDITION", "Type": "DX_NAME", "Traits": []}, {"Id": 58, "BeginOffset": 3505, "EndOffset": 3519, "Score": 0.8299784064292908, "Text": "mental illness", "Category": "MEDICAL_CONDITION", "Type": "DX_NAME", "Traits": [{"Name": "DIAGNOSIS", "Score": 0.5193113088607788}, {"Name": "HYPOTHETICAL", "Score": 0.6583245396614075}]}, {"Id": 59, "BeginOffset": 3521, "EndOffset": 3534, "Score": 0.612697958946228, "Text": "substance use", "Category": "MEDICAL_CONDITION", "Type": "DX_NAME", "Traits": []}, {"Id": 60, "BeginOffset": 3565, "EndOffset": 3571, "Score": 0.6370664834976196, "Text": "trauma", "Category": "MEDICAL_CONDITION", "Type": "DX_NAME", "Traits": [{"Name": "HYPOTHETICAL", "Score": 0.6809278130531311}]}, {"Id": 61, "BeginOffset": 3678, "EndOffset": 3685, "Score": 0.4829338788986206, "Text": "suicide", "Category": "MEDICAL_CONDITION", "Type": "DX_NAME", "Traits": []}, {"Id": 62, "BeginOffset": 3943, "EndOffset": 3951, "Score": 0.4758705794811249, "Text": "COVID-19", "Category": "MEDICAL_CONDITION", "Type": "DX_NAME", "Traits": [{"Name": "DIAGNOSIS", "Score": 0.6198093295097351}]}, {"Id": 63, "BeginOffset": 4140, "EndOffset": 4147, "Score": 0.5357919931411743, "Text": "suicide", "Category": "MEDICAL_CONDITION", "Type": "DX_NAME", "Traits": []}, {"Id": 22, "BeginOffset": 4247, "EndOffset": 4249, "Score": 0.7847133874893188, "Text": "10", "Category": "PROTECTED_HEALTH_INFORMATION", "Type": "AGE", "Traits": []}, {"Id": 64, "BeginOffset": 4585, "EndOffset": 4592, "Score": 0.6270138025283813, "Text": "suicide", "Category": "MEDICAL_CONDITION", "Type": "DX_NAME", "Traits": []}, {"Id": 23, "BeginOffset": 5054, "EndOffset": 5101, "Score": 0.8039642572402954, "Text": "U.S. Substance Abuse and Mental Health Services", "Category": "PROTECTED_HEALTH_INFORMATION", "Type": "ADDRESS", "Traits": []}, {"Id": 65, "BeginOffset": 5059, "EndOffset": 5074, "Score": 0.5533437728881836, "Text": "Substance Abuse", "Category": "MEDICAL_CONDITION", "Type": "DX_NAME", "Traits": [{"Name": "DIAGNOSIS", "Score": 0.526057243347168}]}, {"Id": 24, "BeginOffset": 5119, "EndOffset": 5148, "Score": 0.36201146245002747, "Text": "988 Suicide & Crisis Lifeline", "Category": "PROTECTED_HEALTH_INFORMATION", "Type": "ADDRESS", "Traits": []}, {"Id": 25, "BeginOffset": 5150, "EndOffset": 5173, "Score": 0.930246114730835, "Text": "https://www.988lifeline", "Category": "PROTECTED_HEALTH_INFORMATION", "Type": "URL", "Traits": []}, {"Id": 26, "BeginOffset": 5235, "EndOffset": 5251, "Score": 0.999690055847168, "Text": "Deborah M. Stone", "Category": "PROTECTED_HEALTH_INFORMATION", "Type": "NAME", "Traits": []}, {"Id": 27, "BeginOffset": 5253, "EndOffset": 5265, "Score": 0.984788179397583, "Text": "zaf9@cdc.gov", "Category": "PROTECTED_HEALTH_INFORMATION", "Type": "EMAIL", "Traits": []}, {"Id": 28, "BeginOffset": 5271, "EndOffset": 5318, "Score": 0.250508189201355, "Text": "1Division of Injury Prevention, National Center", "Category": "PROTECTED_HEALTH_INFORMATION", "Type": "ADDRESS", "Traits": []}, {"Id": 66, "BeginOffset": 5323, "EndOffset": 5329, "Score": 0.512894868850708, "Text": "Injury", "Category": "MEDICAL_CONDITION", "Type": "DX_NAME", "Traits": []}, {"Id": 29, "BeginOffset": 5572, "EndOffset": 5598, "Score": 0.9210364818572998, "Text": "https://wonder.cdc.gov/mcd", "Category": "PROTECTED_HEALTH_INFORMATION", "Type": "URL", "Traits": []}, {"Id": 30, "BeginOffset": 5629, "EndOffset": 5645, "Score": 0.9993698000907898, "Text": "January 11, 2023", "Category": "PROTECTED_HEALTH_INFORMATION", "Type": "DATE", "Traits": []}, {"Id": 31, "BeginOffset": 5943, "EndOffset": 5956, "Score": 0.9658781290054321, "Text": "United States", "Category": "PROTECTED_HEALTH_INFORMATION", "Type": "ADDRESS", "Traits": []}, {"Id": 32, "BeginOffset": 5958, "EndOffset": 5967, "Score": 0.9488920569419861, "Text": "2018\u20132021", "Category": "PROTECTED_HEALTH_INFORMATION", "Type": "DATE", "Traits": []}, {"Id": 67, "BeginOffset": 6005, "EndOffset": 6019, "Score": 0.5990737080574036, "Text": "Suicide deaths", "Category": "MEDICAL_CONDITION", "Type": "DX_NAME", "Traits": []}, {"Id": 33, "BeginOffset": 6306, "EndOffset": 6310, "Score": 0.40248146653175354, "Text": "U.S.", "Category": "PROTECTED_HEALTH_INFORMATION", "Type": "ADDRESS", "Traits": []}, {"Id": 34, "BeginOffset": 6318, "EndOffset": 6324, "Score": 0.19981901347637177, "Text": "Bureau", "Category": "PROTECTED_HEALTH_INFORMATION", "Type": "ADDRESS", "Traits": []}, {"Id": 35, "BeginOffset": 6505, "EndOffset": 6511, "Score": 0.558033287525177, "Text": "Alaska", "Category": "PROTECTED_HEALTH_INFORMATION", "Type": "ADDRESS", "Traits": []}, {"Id": 36, "BeginOffset": 7325, "EndOffset": 7329, "Score": 0.16996945440769196, "Text": "2018", "Category": "PROTECTED_HEALTH_INFORMATION", "Type": "DATE", "Traits": []}, {"Id": 37, "BeginOffset": 7389, "EndOffset": 7398, "Score": 0.19674944877624512, "Text": "2018\u20132021", "Category": "PROTECTED_HEALTH_INFORMATION", "Type": "DATE", "Traits": []}, {"Id": 74, "BeginOffset": 7400, "EndOffset": 7401, "Score": 0.7247111201286316, "Text": "p", "Category": "TEST_TREATMENT_PROCEDURE", "Type": "TEST_NAME", "Traits": [], "Attributes": [{"Type": "TEST_VALUE", "Score": 0.6466672420501709, "RelationshipScore": 0.9996191263198853, "RelationshipType": "TEST_VALUE", "Id": 75, "BeginOffset": 7401, "EndOffset": 7406, "Text": "<0.05", "Category": "TEST_TREATMENT_PROCEDURE", "Traits": []}]}, {"Id": 38, "BeginOffset": 7586, "EndOffset": 7602, "Score": 0.999874472618103, "Text": "January 11, 2023", "Category": "PROTECTED_HEALTH_INFORMATION", "Type": "DATE", "Traits": []}, {"Id": 39, "BeginOffset": 7739, "EndOffset": 7759, "Score": 0.9893614649772644, "Text": "Mack KA, Qualters J.", "Category": "PROTECTED_HEALTH_INFORMATION", "Type": "NAME", "Traits": []}, {"Id": 40, "BeginOffset": 7853, "EndOffset": 7866, "Score": 0.8588638305664062, "Text": "United States", "Category": "PROTECTED_HEALTH_INFORMATION", "Type": "ADDRESS", "Traits": []}, {"Id": 41, "BeginOffset": 7868, "EndOffset": 7872, "Score": 0.8721264004707336, "Text": "2021", "Category": "PROTECTED_HEALTH_INFORMATION", "Type": "DATE", "Traits": []}, {"Id": 42, "BeginOffset": 7874, "EndOffset": 7904, "Score": 0.1577776074409485, "Text": "MMWR Morb Mortal Wkly Rep 2023", "Category": "PROTECTED_HEALTH_INFORMATION", "Type": "ADDRESS", "Traits": []}, {"Id": 43, "BeginOffset": 7908, "EndOffset": 7915, "Score": 0.6429819464683533, "Text": "160\u2013162", "Category": "PROTECTED_HEALTH_INFORMATION", "Type": "ID", "Traits": []}, {"Id": 44, "BeginOffset": 7922, "EndOffset": 7948, "Score": 0.9991408586502075, "Text": "http://dx.doi.org/10.15585", "Category": "PROTECTED_HEALTH_INFORMATION", "Type": "URL", "Traits": []}, {"Id": 45, "BeginOffset": 7954, "EndOffset": 7962, "Score": 0.28549477458000183, "Text": "mm7206a4", "Category": "PROTECTED_HEALTH_INFORMATION", "Type": "ID", "Traits": []}, {"Id": 46, "BeginOffset": 8037, "EndOffset": 8081, "Score": 0.9682034850120544, "Text": "U.S. Department of Health and Human Services", "Category": "PROTECTED_HEALTH_INFORMATION", "Type": "ADDRESS", "Traits": []}, {"Id": 47, "BeginOffset": 8191, "EndOffset": 8206, "Score": 0.9088900685310364, "Text": "U.S. Department", "Category": "PROTECTED_HEALTH_INFORMATION", "Type": "ADDRESS", "Traits": []}, {"Id": 48, "BeginOffset": 8427, "EndOffset": 8431, "Score": 0.8909054398536682, "Text": "U.S.", "Category": "PROTECTED_HEALTH_INFORMATION", "Type": "ADDRESS", "Traits": []}, {"Id": 49, "BeginOffset": 8434, "EndOffset": 8473, "Score": 0.7505427598953247, "Text": "Department of Health and Human Services", "Category": "PROTECTED_HEALTH_INFORMATION", "Type": "ADDRESS", "Traits": []}, {"Id": 50, "BeginOffset": 8865, "EndOffset": 8889, "Score": 0.9861841797828674, "Text": "https://www.cdc.gov/mmwr", "Category": "PROTECTED_HEALTH_INFORMATION", "Type": "URL", "Traits": []}, {"Id": 51, "BeginOffset": 9072, "EndOffset": 9085, "Score": 0.8735484480857849, "Text": "mmwrq@cdc.gov", "Category": "PROTECTED_HEALTH_INFORMATION", "Type": "EMAIL", "Traits": []}], "UnmappedAttributes": [{"Type": "TEST_TREATMENT_PROCEDURE", "Attribute": {"Type": "TEST_VALUE", "Score": 0.7785894870758057, "Id": 72, "BeginOffset": 1525, "EndOffset": 1529, "Text": "<100", "Category": "TEST_TREATMENT_PROCEDURE", "Traits": []}}, {"Type": "TEST_TREATMENT_PROCEDURE", "Attribute": {"Type": "TEST_VALUE", "Score": 0.512532651424408, "Id": 76, "BeginOffset": 7637, "EndOffset": 7642, "Text": "<0.05", "Category": "TEST_TREATMENT_PROCEDURE", "Traits": []}}], "ModelVersion": "0.7.0", "ResponseMetadata": {"RequestId": "d76c16de-7df4-468d-9f02-9cd890dc2a62", "HTTPStatusCode": 200, "HTTPHeaders": {"x-amzn-requestid": "d76c16de-7df4-468d-9f02-9cd890dc2a62", "content-type": "application/x-amz-json-1.1", "content-length": "13081", "date": "Tue, 20 Jun 2023 18:00:49 GMT"}, "RetryAttempts": 0}}