{"Entities": [{"Id": 1, "BeginOffset": 131, "EndOffset": 144, "Score": 0.3932449519634247, "Text": "United States", "Category": "PROTECTED_HEALTH_INFORMATION", "Type": "ADDRESS", "Traits": []}, {"Id": 2, "BeginOffset": 146, "EndOffset": 174, "Score": 0.9995077848434448, "Text": "November 2021\u00e2\u0080\u0093January 2023", "Category": "PROTECTED_HEALTH_INFORMATION", "Type": "DATE", "Traits": []}, {"Id": 3, "BeginOffset": 184, "EndOffset": 200, "Score": 0.9971959590911865, "Text": "February 3, 2023", "Category": "PROTECTED_HEALTH_INFORMATION", "Type": "DATE", "Traits": []}, {"Id": 4, "BeginOffset": 223, "EndOffset": 239, "Score": 0.9999494552612305, "Text": "January 25, 2023", "Category": "PROTECTED_HEALTH_INFORMATION", "Type": "DATE", "Traits": []}, {"Id": 5, "BeginOffset": 297, "EndOffset": 314, "Score": 0.9989389777183533, "Text": "Heather M. Scobie", "Category": "PROTECTED_HEALTH_INFORMATION", "Type": "NAME", "Traits": []}, {"Id": 6, "BeginOffset": 322, "EndOffset": 335, "Score": 0.9989376664161682, "Text": "Akilah R. Ali", "Category": "PROTECTED_HEALTH_INFORMATION", "Type": "NAME", "Traits": []}, {"Id": 7, "BeginOffset": 343, "EndOffset": 355, "Score": 0.9998829364776611, "Text": "Philip Shirk", "Category": "PROTECTED_HEALTH_INFORMATION", "Type": "NAME", "Traits": []}, {"Id": 8, "BeginOffset": 363, "EndOffset": 379, "Score": 0.9996263980865479, "Text": "Zachary R. Smith", "Category": "PROTECTED_HEALTH_INFORMATION", "Type": "NAME", "Traits": []}, {"Id": 9, "BeginOffset": 386, "EndOffset": 399, "Score": 0.999408483505249, "Text": "Prabasaj Paul", "Category": "PROTECTED_HEALTH_INFORMATION", "Type": "NAME", "Traits": []}, {"Id": 10, "BeginOffset": 407, "EndOffset": 423, "Score": 0.9988052845001221, "Text": "Clinton R. Paden", "Category": "PROTECTED_HEALTH_INFORMATION", "Type": "NAME", "Traits": []}, {"Id": 11, "BeginOffset": 431, "EndOffset": 445, "Score": 0.9999513626098633, "Text": "Norman Hassell", "Category": "PROTECTED_HEALTH_INFORMATION", "Type": "NAME", "Traits": []}, {"Id": 12, "BeginOffset": 452, "EndOffset": 465, "Score": 0.9780656695365906, "Text": "Xiao-yu Zheng", "Category": "PROTECTED_HEALTH_INFORMATION", "Type": "NAME", "Traits": []}, {"Id": 13, "BeginOffset": 473, "EndOffset": 493, "Score": 0.9987902045249939, "Text": "Anastasia S. Lambrou", "Category": "PROTECTED_HEALTH_INFORMATION", "Type": "NAME", "Traits": []}, {"Id": 14, "BeginOffset": 503, "EndOffset": 517, "Score": 0.999431312084198, "Text": "Rebecca Kondor", "Category": "PROTECTED_HEALTH_INFORMATION", "Type": "NAME", "Traits": []}, {"Id": 15, "BeginOffset": 525, "EndOffset": 542, "Score": 0.9997870326042175, "Text": "Duncan MacCannell", "Category": "PROTECTED_HEALTH_INFORMATION", "Type": "NAME", "Traits": []}, {"Id": 16, "BeginOffset": 550, "EndOffset": 570, "Score": 0.9982176423072815, "Text": "Natalie J. Thornburg", "Category": "PROTECTED_HEALTH_INFORMATION", "Type": "NAME", "Traits": []}, {"Id": 17, "BeginOffset": 578, "EndOffset": 591, "Score": 0.999967098236084, "Text": "Joseph Miller", "Category": "PROTECTED_HEALTH_INFORMATION", "Type": "NAME", "Traits": []}, {"Id": 18, "BeginOffset": 599, "EndOffset": 613, "Score": 0.9998606443405151, "Text": "Dave Wentworth", "Category": "PROTECTED_HEALTH_INFORMATION", "Type": "NAME", "Traits": []}, {"Id": 19, "BeginOffset": 621, "EndOffset": 637, "Score": 0.9874799847602844, "Text": "Benjamin J. Silk", "Category": "PROTECTED_HEALTH_INFORMATION", "Type": "NAME", "Traits": []}, {"Id": 72, "BeginOffset": 995, "EndOffset": 1019, "Score": 0.5417962670326233, "Text": "SARS-CoV-2 Alpha variant", "Category": "MEDICAL_CONDITION", "Type": "DX_NAME", "Traits": [{"Name": "DIAGNOSIS", "Score": 0.734961211681366}]}, {"Id": 20, "BeginOffset": 1036, "EndOffset": 1040, "Score": 0.5708233118057251, "Text": "2020", "Category": "PROTECTED_HEALTH_INFORMATION", "Type": "DATE", "Traits": []}, {"Id": 73, "BeginOffset": 1044, "EndOffset": 1072, "Score": 0.5962015986442566, "Text": "spike gene (S-gene) deletion", "Category": "MEDICAL_CONDITION", "Type": "DX_NAME", "Traits": []}, {"Id": 89, "BeginOffset": 1089, "EndOffset": 1106, "Score": 0.7110165357589722, "Text": "N-terminal region", "Category": "ANATOMY", "Type": "SYSTEM_ORGAN_SITE", "Traits": []}, {"Id": 74, "BeginOffset": 1135, "EndOffset": 1158, "Score": 0.6107363104820251, "Text": "immune escape mutations", "Category": "MEDICAL_CONDITION", "Type": "DX_NAME", "Traits": []}, {"Id": 75, "BeginOffset": 1164, "EndOffset": 1182, "Score": 0.3733558654785156, "Text": "impair infectivity", "Category": "MEDICAL_CONDITION", "Type": "DX_NAME", "Traits": []}, {"Id": 76, "BeginOffset": 1620, "EndOffset": 1640, "Score": 0.4809116721153259, "Text": "Omicron BA.5\u2013related", "Category": "MEDICAL_CONDITION", "Type": "DX_NAME", "Traits": []}, {"Id": 77, "BeginOffset": 1715, "EndOffset": 1719, "Score": 0.7195020914077759, "Text": "SGTP", "Category": "MEDICAL_CONDITION", "Type": "DX_NAME", "Traits": [{"Name": "DIAGNOSIS", "Score": 0.6759694814682007}]}, {"Id": 21, "BeginOffset": 1748, "EndOffset": 1774, "Score": 0.9790904521942139, "Text": "northeastern United States", "Category": "PROTECTED_HEALTH_INFORMATION", "Type": "ADDRESS", "Traits": []}, {"Id": 91, "BeginOffset": 2072, "EndOffset": 2074, "Score": 0.8237991333007812, "Text": "Ct", "Category": "TEST_TREATMENT_PROCEDURE", "Type": "TEST_NAME", "Traits": []}, {"Id": 22, "BeginOffset": 2143, "EndOffset": 2158, "Score": 0.9452128410339355, "Text": "U.S. Department", "Category": "PROTECTED_HEALTH_INFORMATION", "Type": "ADDRESS", "Traits": []}, {"Id": 23, "BeginOffset": 2210, "EndOffset": 2243, "Score": 0.9987749457359314, "Text": "November 1, 2021\u2013January 14, 2023", "Category": "PROTECTED_HEALTH_INFORMATION", "Type": "DATE", "Traits": []}, {"Id": 92, "BeginOffset": 2402, "EndOffset": 2405, "Score": 0.4908197820186615, "Text": "CDC", "Category": "TEST_TREATMENT_PROCEDURE", "Type": "TEST_NAME", "Traits": []}, {"Id": 93, "BeginOffset": 2453, "EndOffset": 2472, "Score": 0.4034166932106018, "Text": "National SARS-CoV-2", "Category": "TEST_TREATMENT_PROCEDURE", "Type": "TEST_NAME", "Traits": []}, {"Id": 24, "BeginOffset": 2586, "EndOffset": 2592, "Score": 0.2989882826805115, "Text": "public", "Category": "PROTECTED_HEALTH_INFORMATION", "Type": "ADDRESS", "Traits": []}, {"Id": 25, "BeginOffset": 2895, "EndOffset": 2929, "Score": 0.9988771080970764, "Text": "December 25, 2022\u2013January 14, 2023", "Category": "PROTECTED_HEALTH_INFORMATION", "Type": "DATE", "Traits": []}, {"Id": 26, "BeginOffset": 3418, "EndOffset": 3452, "Score": 0.9958510398864746, "Text": "November 1, 2021\u2013December 24, 2022", "Category": "PROTECTED_HEALTH_INFORMATION", "Type": "DATE", "Traits": []}, {"Id": 94, "BeginOffset": 3470, "EndOffset": 3474, "Score": 0.8065394759178162, "Text": "SGTF", "Category": "TEST_TREATMENT_PROCEDURE", "Type": "TEST_NAME", "Traits": []}, {"Id": 95, "BeginOffset": 3479, "EndOffset": 3483, "Score": 0.4996070861816406, "Text": "SGTP", "Category": "TEST_TREATMENT_PROCEDURE", "Type": "TEST_NAME", "Traits": []}, {"Id": 27, "BeginOffset": 3679, "EndOffset": 3713, "Score": 0.9986422657966614, "Text": "December 25, 2022\u2013January 14, 2023", "Category": "PROTECTED_HEALTH_INFORMATION", "Type": "DATE", "Traits": []}, {"Id": 28, "BeginOffset": 4106, "EndOffset": 4123, "Score": 0.9999353885650635, "Text": "December 24, 2022", "Category": "PROTECTED_HEALTH_INFORMATION", "Type": "DATE", "Traits": []}, {"Id": 99, "BeginOffset": 4357, "EndOffset": 4370, "Score": 0.3779815435409546, "Text": "SGTP estimate", "Category": "TEST_TREATMENT_PROCEDURE", "Type": "TEST_NAME", "Traits": [], "Attributes": [{"Type": "TEST_VALUE", "Score": 0.7816310524940491, "RelationshipScore": 0.9844751954078674, "RelationshipType": "TEST_VALUE", "Id": 100, "BeginOffset": 4386, "EndOffset": 4388, "Text": "20", "Category": "TEST_TREATMENT_PROCEDURE", "Traits": []}, {"Type": "TEST_UNIT", "Score": 0.8265931606292725, "RelationshipScore": 0.7119158506393433, "RelationshipType": "TEST_UNIT", "Id": 101, "BeginOffset": 4388, "EndOffset": 4389, "Text": "%", "Category": "TEST_TREATMENT_PROCEDURE", "Traits": []}]}, {"Id": 29, "BeginOffset": 4430, "EndOffset": 4446, "Score": 0.9998131394386292, "Text": "January 14, 2023", "Category": "PROTECTED_HEALTH_INFORMATION", "Type": "DATE", "Traits": []}, {"Id": 102, "BeginOffset": 4452, "EndOffset": 4465, "Score": 0.6602135896682739, "Text": "SGTP estimate", "Category": "TEST_TREATMENT_PROCEDURE", "Type": "TEST_NAME", "Traits": [], "Attributes": [{"Type": "TEST_VALUE", "Score": 0.7821250557899475, "RelationshipScore": 0.9625068306922913, "RelationshipType": "TEST_VALUE", "Id": 103, "BeginOffset": 4481, "EndOffset": 4483, "Text": "40", "Category": "TEST_TREATMENT_PROCEDURE", "Traits": []}]}, {"Id": 105, "BeginOffset": 4490, "EndOffset": 4493, "Score": 0.389757364988327, "Text": "CI\u00a0", "Category": "TEST_TREATMENT_PROCEDURE", "Type": "TEST_NAME", "Traits": []}, {"Id": 30, "BeginOffset": 4667, "EndOffset": 4683, "Score": 0.9992757439613342, "Text": "January 13, 2023", "Category": "PROTECTED_HEALTH_INFORMATION", "Type": "DATE", "Traits": []}, {"Id": 108, "BeginOffset": 4712, "EndOffset": 4715, "Score": 0.46169313788414, "Text": "XBB", "Category": "TEST_TREATMENT_PROCEDURE", "Type": "TEST_NAME", "Traits": [], "Attributes": [{"Type": "TEST_VALUE", "Score": 0.7289898991584778, "RelationshipScore": 0.9768564105033875, "RelationshipType": "TEST_VALUE", "Id": 109, "BeginOffset": 4718, "EndOffset": 4722, "Text": "4.0%", "Category": "TEST_TREATMENT_PROCEDURE", "Traits": []}]}, {"Id": 31, "BeginOffset": 4846, "EndOffset": 4862, "Score": 0.9993656277656555, "Text": "January 20, 2023", "Category": "PROTECTED_HEALTH_INFORMATION", "Type": "DATE", "Traits": []}, {"Id": 32, "BeginOffset": 5034, "EndOffset": 5072, "Score": 0.9135257005691528, "Text": "https://stacks.cdc.gov/view/cdc/123810", "Category": "PROTECTED_HEALTH_INFORMATION", "Type": "URL", "Traits": []}, {"Id": 33, "BeginOffset": 5138, "EndOffset": 5153, "Score": 0.9994465708732605, "Text": "January 2, 2023", "Category": "PROTECTED_HEALTH_INFORMATION", "Type": "DATE", "Traits": []}, {"Id": 34, "BeginOffset": 5239, "EndOffset": 5271, "Score": 0.9976149797439575, "Text": "December 1, 2022\u2013January 2, 2023", "Category": "PROTECTED_HEALTH_INFORMATION", "Type": "DATE", "Traits": []}, {"Id": 112, "BeginOffset": 5363, "EndOffset": 5380, "Score": 0.39269670844078064, "Text": "diagnostic RT-PCR", "Category": "TEST_TREATMENT_PROCEDURE", "Type": "TEST_NAME", "Traits": [], "Attributes": [{"Type": "TEST_VALUE", "Score": 0.4847427010536194, "RelationshipScore": 0.5979371070861816, "RelationshipType": "TEST_VALUE", "Id": 113, "BeginOffset": 5391, "EndOffset": 5405, "Text": "less expensive", "Category": "TEST_TREATMENT_PROCEDURE", "Traits": []}]}, {"Id": 114, "BeginOffset": 5972, "EndOffset": 5993, "Score": 0.5506888628005981, "Text": "SARS-CoV-2 sequencing", "Category": "TEST_TREATMENT_PROCEDURE", "Type": "TEST_NAME", "Traits": []}, {"Id": 115, "BeginOffset": 6374, "EndOffset": 6377, "Score": 0.5284821391105652, "Text": "CDC", "Category": "TEST_TREATMENT_PROCEDURE", "Type": "PROCEDURE_NAME", "Traits": []}, {"Id": 116, "BeginOffset": 6449, "EndOffset": 6478, "Score": 0.8828303217887878, "Text": "monoclonal antibody therapies", "Category": "TEST_TREATMENT_PROCEDURE", "Type": "TREATMENT_NAME", "Traits": []}, {"Id": 35, "BeginOffset": 6775, "EndOffset": 6790, "Score": 0.7714104652404785, "Text": "Summer Galloway", "Category": "PROTECTED_HEALTH_INFORMATION", "Type": "NAME", "Traits": []}, {"Id": 117, "BeginOffset": 6792, "EndOffset": 6795, "Score": 0.47419798374176025, "Text": "CDC", "Category": "TEST_TREATMENT_PROCEDURE", "Type": "TEST_NAME", "Traits": []}, {"Id": 36, "BeginOffset": 6892, "EndOffset": 6910, "Score": 0.9459925889968872, "Text": "Aegis Sciences Lab", "Category": "PROTECTED_HEALTH_INFORMATION", "Type": "ADDRESS", "Traits": []}, {"Id": 37, "BeginOffset": 6915, "EndOffset": 6928, "Score": 0.9105293154716492, "Text": "Walgreens Co.", "Category": "PROTECTED_HEALTH_INFORMATION", "Type": "ADDRESS", "Traits": []}, {"Id": 38, "BeginOffset": 6955, "EndOffset": 6972, "Score": 0.9994578957557678, "Text": "Heather M. Scobie", "Category": "PROTECTED_HEALTH_INFORMATION", "Type": "NAME", "Traits": []}, {"Id": 39, "BeginOffset": 6974, "EndOffset": 6989, "Score": 0.9922560453414917, "Text": "hscobie@cdc.gov", "Category": "PROTECTED_HEALTH_INFORMATION", "Type": "EMAIL", "Traits": []}, {"Id": 40, "BeginOffset": 6995, "EndOffset": 7011, "Score": 0.7703296542167664, "Text": "1National Center", "Category": "PROTECTED_HEALTH_INFORMATION", "Type": "ADDRESS", "Traits": []}, {"Id": 90, "BeginOffset": 7033, "EndOffset": 7044, "Score": 0.7782065868377686, "Text": "Respiratory", "Category": "ANATOMY", "Type": "SYSTEM_ORGAN_SITE", "Traits": []}, {"Id": 79, "BeginOffset": 7033, "EndOffset": 7053, "Score": 0.8859215974807739, "Text": "Respiratory Diseases", "Category": "MEDICAL_CONDITION", "Type": "DX_NAME", "Traits": [{"Name": "DIAGNOSIS", "Score": 0.9386693239212036}], "Attributes": [{"Type": "SYSTEM_ORGAN_SITE", "Score": 0.7782065868377686, "RelationshipScore": 0.7860680222511292, "RelationshipType": "SYSTEM_ORGAN_SITE", "Id": 90, "BeginOffset": 7033, "EndOffset": 7044, "Text": "Respiratory", "Category": "ANATOMY", "Traits": []}]}, {"Id": 41, "BeginOffset": 7104, "EndOffset": 7120, "Score": 0.4126116633415222, "Text": "3National Center", "Category": "PROTECTED_HEALTH_INFORMATION", "Type": "ADDRESS", "Traits": []}, {"Id": 80, "BeginOffset": 7147, "EndOffset": 7166, "Score": 0.6589893102645874, "Text": "Infectious Diseases", "Category": "MEDICAL_CONDITION", "Type": "DX_NAME", "Traits": [{"Name": "DIAGNOSIS", "Score": 0.7537065148353577}]}, {"Id": 42, "BeginOffset": 7429, "EndOffset": 7470, "Score": 0.9880853891372681, "Text": "https://www.cdc.gov/icatt/AboutICATT.html", "Category": "PROTECTED_HEALTH_INFORMATION", "Type": "URL", "Traits": []}, {"Id": 118, "BeginOffset": 7649, "EndOffset": 7662, "Score": 0.4924720823764801, "Text": "COVID-19 data", "Category": "TEST_TREATMENT_PROCEDURE", "Type": "TEST_NAME", "Traits": []}, {"Id": 43, "BeginOffset": 7744, "EndOffset": 7793, "Score": 0.9684699773788452, "Text": "https://www.cdc.gov/ncezid/hhs-protect/index.html", "Category": "PROTECTED_HEALTH_INFORMATION", "Type": "URL", "Traits": []}, {"Id": 119, "BeginOffset": 7819, "EndOffset": 7821, "Score": 0.4289943277835846, "Text": "Ct", "Category": "TEST_TREATMENT_PROCEDURE", "Type": "TEST_NAME", "Traits": []}, {"Id": 120, "BeginOffset": 7860, "EndOffset": 7864, "Score": 0.7797175645828247, "Text": "SGTF", "Category": "TEST_TREATMENT_PROCEDURE", "Type": "TEST_NAME", "Traits": []}, {"Id": 121, "BeginOffset": 8078, "EndOffset": 8080, "Score": 0.5687263011932373, "Text": "Ct", "Category": "TEST_TREATMENT_PROCEDURE", "Type": "TEST_NAME", "Traits": []}, {"Id": 122, "BeginOffset": 8090, "EndOffset": 8109, "Score": 0.5364411473274231, "Text": "SARS-CoV-2\u2013positive", "Category": "TEST_TREATMENT_PROCEDURE", "Type": "TEST_NAME", "Traits": []}, {"Id": 123, "BeginOffset": 8155, "EndOffset": 8159, "Score": 0.40035220980644226, "Text": "SGTP", "Category": "TEST_TREATMENT_PROCEDURE", "Type": "PROCEDURE_NAME", "Traits": []}, {"Id": 44, "BeginOffset": 8163, "EndOffset": 8229, "Score": 0.9905931353569031, "Text": "https://www.hhs.gov/about/agencies/iea/regional-offices/index.html", "Category": "PROTECTED_HEALTH_INFORMATION", "Type": "URL", "Traits": []}, {"Id": 45, "BeginOffset": 8377, "EndOffset": 8520, "Score": 0.9922189712524414, "Text": "https://www.walgreens.com/businesssolutions/covid-19-index.jsp\n\u2020\u2020 https://www.cdc.gov/coronavirus/2019-ncov/variants/cdc-role-surveillance.html", "Category": "PROTECTED_HEALTH_INFORMATION", "Type": "URL", "Traits": []}, {"Id": 124, "BeginOffset": 8421, "EndOffset": 8435, "Score": 0.49940693378448486, "Text": "covid-19-index", "Category": "TEST_TREATMENT_PROCEDURE", "Type": "TEST_NAME", "Traits": []}, {"Id": 46, "BeginOffset": 8524, "EndOffset": 8551, "Score": 0.9699046015739441, "Text": "https://covid.cdc.gov/covid", "Category": "PROTECTED_HEALTH_INFORMATION", "Type": "URL", "Traits": []}, {"Id": 47, "BeginOffset": 8604, "EndOffset": 8616, "Score": 0.6492212414741516, "Text": "46.102(l)(2)", "Category": "PROTECTED_HEALTH_INFORMATION", "Type": "DATE", "Traits": []}, {"Id": 48, "BeginOffset": 8738, "EndOffset": 8758, "Score": 0.8757087588310242, "Text": "District of Columbia", "Category": "PROTECTED_HEALTH_INFORMATION", "Type": "ADDRESS", "Traits": []}, {"Id": 49, "BeginOffset": 8764, "EndOffset": 8775, "Score": 0.7796886563301086, "Text": "Puerto Rico", "Category": "PROTECTED_HEALTH_INFORMATION", "Type": "ADDRESS", "Traits": []}, {"Id": 50, "BeginOffset": 8799, "EndOffset": 8819, "Score": 0.23286288976669312, "Text": "District of Columbia", "Category": "PROTECTED_HEALTH_INFORMATION", "Type": "ADDRESS", "Traits": []}, {"Id": 51, "BeginOffset": 8843, "EndOffset": 8902, "Score": 0.7242335677146912, "Text": "American Samoa, Guam, Northern Mariana Islands, Puerto Rico", "Category": "PROTECTED_HEALTH_INFORMATION", "Type": "ADDRESS", "Traits": []}, {"Id": 52, "BeginOffset": 8912, "EndOffset": 8931, "Score": 0.7969456315040588, "Text": "U.S. Virgin Islands", "Category": "PROTECTED_HEALTH_INFORMATION", "Type": "PROFESSION", "Traits": []}, {"Id": 53, "BeginOffset": 8990, "EndOffset": 9006, "Score": 0.999612033367157, "Text": "January 14, 2023", "Category": "PROTECTED_HEALTH_INFORMATION", "Type": "DATE", "Traits": []}, {"Id": 54, "BeginOffset": 9080, "EndOffset": 9096, "Score": 0.9998679161071777, "Text": "January 13, 2023", "Category": "PROTECTED_HEALTH_INFORMATION", "Type": "DATE", "Traits": []}, {"Id": 81, "BeginOffset": 9169, "EndOffset": 9172, "Score": 0.6421840786933899, "Text": "XBB", "Category": "MEDICAL_CONDITION", "Type": "DX_NAME", "Traits": [{"Name": "DIAGNOSIS", "Score": 0.6161591410636902}]}, {"Id": 55, "BeginOffset": 9223, "EndOffset": 9239, "Score": 0.9999040365219116, "Text": "January 20, 2023", "Category": "PROTECTED_HEALTH_INFORMATION", "Type": "DATE", "Traits": []}, {"Id": 129, "BeginOffset": 9257, "EndOffset": 9259, "Score": 0.5805068016052246, "Text": "PI", "Category": "TEST_TREATMENT_PROCEDURE", "Type": "TEST_NAME", "Traits": []}, {"Id": 82, "BeginOffset": 9321, "EndOffset": 9324, "Score": 0.6872448921203613, "Text": "XBB", "Category": "MEDICAL_CONDITION", "Type": "DX_NAME", "Traits": [{"Name": "DIAGNOSIS", "Score": 0.6766105890274048}]}, {"Id": 56, "BeginOffset": 9411, "EndOffset": 9489, "Score": 0.9385870099067688, "Text": "https://www.cdc.gov/coronavirus/2019-ncov/variants/variant-classifications.htm", "Category": "PROTECTED_HEALTH_INFORMATION", "Type": "URL", "Traits": []}, {"Id": 57, "BeginOffset": 9792, "EndOffset": 9805, "Score": 0.5267875790596008, "Text": "United States", "Category": "PROTECTED_HEALTH_INFORMATION", "Type": "ADDRESS", "Traits": []}, {"Id": 58, "BeginOffset": 9807, "EndOffset": 9840, "Score": 0.9999010562896729, "Text": "November 1, 2021\u2013January 14, 2023", "Category": "PROTECTED_HEALTH_INFORMATION", "Type": "DATE", "Traits": []}, {"Id": 83, "BeginOffset": 10078, "EndOffset": 10082, "Score": 0.52299964427948, "Text": "SGTP", "Category": "MEDICAL_CONDITION", "Type": "DX_NAME", "Traits": []}, {"Id": 84, "BeginOffset": 10088, "EndOffset": 10095, "Score": 0.4054451882839203, "Text": "Omicron", "Category": "MEDICAL_CONDITION", "Type": "DX_NAME", "Traits": []}, {"Id": 85, "BeginOffset": 10148, "EndOffset": 10152, "Score": 0.5958990454673767, "Text": "SGTF", "Category": "MEDICAL_CONDITION", "Type": "DX_NAME", "Traits": []}, {"Id": 86, "BeginOffset": 10207, "EndOffset": 10211, "Score": 0.5479598641395569, "Text": "SGTP", "Category": "MEDICAL_CONDITION", "Type": "DX_NAME", "Traits": []}, {"Id": 87, "BeginOffset": 10478, "EndOffset": 10482, "Score": 0.604153037071228, "Text": "SGTP", "Category": "MEDICAL_CONDITION", "Type": "DX_NAME", "Traits": []}, {"Id": 130, "BeginOffset": 10528, "EndOffset": 10532, "Score": 0.6854687333106995, "Text": "SGTF", "Category": "TEST_TREATMENT_PROCEDURE", "Type": "TEST_NAME", "Traits": []}, {"Id": 59, "BeginOffset": 10719, "EndOffset": 10743, "Score": 0.7466661334037781, "Text": "Scobie HM, Ali AR, Shirk", "Category": "PROTECTED_HEALTH_INFORMATION", "Type": "NAME", "Traits": []}, {"Id": 88, "BeginOffset": 10861, "EndOffset": 10871, "Score": 0.7400447726249695, "Text": "SARS-CoV-2", "Category": "MEDICAL_CONDITION", "Type": "DX_NAME", "Traits": [{"Name": "DIAGNOSIS", "Score": 0.6435309052467346}]}, {"Id": 60, "BeginOffset": 10883, "EndOffset": 10896, "Score": 0.8868070244789124, "Text": "United States", "Category": "PROTECTED_HEALTH_INFORMATION", "Type": "ADDRESS", "Traits": []}, {"Id": 61, "BeginOffset": 10898, "EndOffset": 10924, "Score": 0.999713122844696, "Text": "November 2021\u2013January 2023", "Category": "PROTECTED_HEALTH_INFORMATION", "Type": "DATE", "Traits": []}, {"Id": 62, "BeginOffset": 10960, "EndOffset": 10967, "Score": 0.23435992002487183, "Text": "125\u2013127", "Category": "PROTECTED_HEALTH_INFORMATION", "Type": "ID", "Traits": []}, {"Id": 63, "BeginOffset": 10974, "EndOffset": 11000, "Score": 0.9996486902236938, "Text": "http://dx.doi.org/10.15585", "Category": "PROTECTED_HEALTH_INFORMATION", "Type": "URL", "Traits": []}, {"Id": 64, "BeginOffset": 11006, "EndOffset": 11014, "Score": 0.4964900314807892, "Text": "mm7205e2", "Category": "PROTECTED_HEALTH_INFORMATION", "Type": "ID", "Traits": []}, {"Id": 65, "BeginOffset": 11089, "EndOffset": 11104, "Score": 0.9665443897247314, "Text": "U.S. Department", "Category": "PROTECTED_HEALTH_INFORMATION", "Type": "ADDRESS", "Traits": []}, {"Id": 66, "BeginOffset": 11243, "EndOffset": 11258, "Score": 0.9496952891349792, "Text": "U.S. Department", "Category": "PROTECTED_HEALTH_INFORMATION", "Type": "ADDRESS", "Traits": []}, {"Id": 67, "BeginOffset": 11366, "EndOffset": 11370, "Score": 0.15077953040599823, "Text": "MMWR", "Category": "PROTECTED_HEALTH_INFORMATION", "Type": "ADDRESS", "Traits": []}, {"Id": 68, "BeginOffset": 11479, "EndOffset": 11483, "Score": 0.8876439332962036, "Text": "U.S.", "Category": "PROTECTED_HEALTH_INFORMATION", "Type": "ADDRESS", "Traits": []}, {"Id": 69, "BeginOffset": 11486, "EndOffset": 11525, "Score": 0.8135976791381836, "Text": "Department of Health and Human Services", "Category": "PROTECTED_HEALTH_INFORMATION", "Type": "ADDRESS", "Traits": []}, {"Id": 70, "BeginOffset": 11917, "EndOffset": 11941, "Score": 0.9850202798843384, "Text": "https://www.cdc.gov/mmwr", "Category": "PROTECTED_HEALTH_INFORMATION", "Type": "URL", "Traits": []}, {"Id": 71, "BeginOffset": 12124, "EndOffset": 12137, "Score": 0.8620180487632751, "Text": "mmwrq@cdc.gov", "Category": "PROTECTED_HEALTH_INFORMATION", "Type": "EMAIL", "Traits": []}], "UnmappedAttributes": [{"Type": "MEDICAL_CONDITION", "Attribute": {"Type": "QUALITY", "Score": 0.4315911531448364, "Id": 78, "BeginOffset": 1724, "EndOffset": 1740, "Text": "rapidly expanded", "Category": "MEDICAL_CONDITION", "Traits": []}}, {"Type": "TEST_TREATMENT_PROCEDURE", "Attribute": {"Type": "TEST_VALUE", "Score": 0.46245378255844116, "Id": 96, "BeginOffset": 4259, "EndOffset": 4264, "Text": "\u00a011.8", "Category": "TEST_TREATMENT_PROCEDURE", "Traits": []}}, {"Type": "TEST_TREATMENT_PROCEDURE", "Attribute": {"Type": "TEST_VALUE", "Score": 0.716417133808136, "Id": 97, "BeginOffset": 4272, "EndOffset": 4276, "Text": "\u00a04.4", "Category": "TEST_TREATMENT_PROCEDURE", "Traits": []}}, {"Type": "TEST_TREATMENT_PROCEDURE", "Attribute": {"Type": "TEST_UNIT", "Score": 0.5197630524635315, "Id": 98, "BeginOffset": 4276, "EndOffset": 4277, "Text": "%", "Category": "TEST_TREATMENT_PROCEDURE", "Traits": []}}, {"Type": "TEST_TREATMENT_PROCEDURE", "Attribute": {"Type": "TEST_UNIT", "Score": 0.8142960071563721, "Id": 104, "BeginOffset": 4483, "EndOffset": 4484, "Text": "%", "Category": "TEST_TREATMENT_PROCEDURE", "Traits": []}}, {"Type": "TEST_TREATMENT_PROCEDURE", "Attribute": {"Type": "TEST_VALUE", "Score": 0.7172770500183105, "Id": 106, "BeginOffset": 4575, "EndOffset": 4579, "Text": "3.9%", "Category": "TEST_TREATMENT_PROCEDURE", "Traits": []}}, {"Type": "TEST_TREATMENT_PROCEDURE", "Attribute": {"Type": "TEST_VALUE", "Score": 0.4612749218940735, "Id": 107, "BeginOffset": 4705, "EndOffset": 4710, "Text": "37.2%", "Category": "TEST_TREATMENT_PROCEDURE", "Traits": []}}, {"Type": "TEST_TREATMENT_PROCEDURE", "Attribute": {"Type": "TEST_VALUE", "Score": 0.5153800845146179, "Id": 110, "BeginOffset": 5273, "EndOffset": 5276, "Text": "294", "Category": "TEST_TREATMENT_PROCEDURE", "Traits": []}}, {"Type": "TEST_TREATMENT_PROCEDURE", "Attribute": {"Type": "TEST_VALUE", "Score": 0.4298914670944214, "Id": 111, "BeginOffset": 5286, "EndOffset": 5289, "Text": "495", "Category": "TEST_TREATMENT_PROCEDURE", "Traits": []}}, {"Type": "TEST_TREATMENT_PROCEDURE", "Attribute": {"Type": "TEST_VALUE", "Score": 0.8626964092254639, "Id": 125, "BeginOffset": 9103, "EndOffset": 9107, "Text": "43.0", "Category": "TEST_TREATMENT_PROCEDURE", "Traits": []}}, {"Type": "TEST_TREATMENT_PROCEDURE", "Attribute": {"Type": "TEST_UNIT", "Score": 0.6748769283294678, "Id": 126, "BeginOffset": 9107, "EndOffset": 9108, "Text": "%", "Category": "TEST_TREATMENT_PROCEDURE", "Traits": []}}, {"Type": "TEST_TREATMENT_PROCEDURE", "Attribute": {"Type": "TEST_VALUE", "Score": 0.8025136590003967, "Id": 127, "BeginOffset": 9246, "EndOffset": 9250, "Text": "37.2", "Category": "TEST_TREATMENT_PROCEDURE", "Traits": []}}, {"Type": "TEST_TREATMENT_PROCEDURE", "Attribute": {"Type": "TEST_UNIT", "Score": 0.5990284085273743, "Id": 128, "BeginOffset": 9250, "EndOffset": 9251, "Text": "%", "Category": "TEST_TREATMENT_PROCEDURE", "Traits": []}}], "ModelVersion": "0.7.0", "ResponseMetadata": {"RequestId": "cf56373c-907d-47ca-ab19-005a0bb10bf7", "HTTPStatusCode": 200, "HTTPHeaders": {"x-amzn-requestid": "cf56373c-907d-47ca-ab19-005a0bb10bf7", "content-type": "application/x-amz-json-1.1", "content-length": "23416", "date": "Tue, 20 Jun 2023 18:00:53 GMT"}, "RetryAttempts": 0}}